reflex_magic_link_auth/__init__.py
reflex_magic_link_auth/constants.py
reflex_magic_link_auth/page.py
reflex_magic_link_auth/state.py
reflex_magic_link_auth/models/__init__.py
reflex_magic_link_auth/models/record.py
reflex_magic_link_auth/models/session.py
reflex_magic_link_auth/providers/__init__.py
reflex_magic_link_auth/providers/mailgun.py
reflex_magic_link_auth-0.2.0.post1.dist-info/METADATA
reflex_magic_link_auth-0.2.0.post1.dist-info/WHEEL
reflex_magic_link_auth-0.2.0.post1.dist-info/top_level.txt
reflex_magic_link_auth-0.2.0.post1.dist-info/RECORD
