Metadata-Version: 2.4
Name: reflex-magic-link-auth
Version: 0.2.0.post1
Summary: Login with magic links sent via email
Author-email: Masen Furer <m_github@0x26.net>
License: Apache-2.0
Project-URL: Homepage, https://github.com/masenf/reflex-magic-link-auth
Keywords: reflex,reflex-custom-components
Classifier: Development Status :: 4 - Beta
Requires-Python: >=3.10
Requires-Dist: reflex>=0.8.4
Requires-Dist: bcrypt
Requires-Dist: httpx
Provides-Extra: dev
Requires-Dist: build; extra == "dev"
Requires-Dist: twine; extra == "dev"
